.gitignore
CHANGES.rst
README.rst
setup.py
src/buster_selenium/__init__.py
src/buster_selenium/case.py
src/buster_selenium/find.py
src/buster_selenium/layer.py
src/buster_selenium/recipe.py
src/buster_selenium/runner.py
src/buster_selenium.egg-info/PKG-INFO
src/buster_selenium.egg-info/SOURCES.txt
src/buster_selenium.egg-info/dependency_links.txt
src/buster_selenium.egg-info/entry_points.txt
src/buster_selenium.egg-info/requires.txt
src/buster_selenium.egg-info/top_level.txt