Metadata-Version: 1.1
Name: buster-selenium
Version: 0.1
Summary: Manage buster.js slave browsers using selenium.
Home-page: http://github.com/plone/buster-selenium
Author: Ross Patterson
Author-email: me@rpatterson.net
License: GPL
Keywords: buster selenium js javascript ecmascript
Platform: UNKNOWN
Classifier: Programming Language :: Python
Classifier: Topic :: Software Development :: Libraries :: Python Modules
